api/__init__.py
api/config.py
api/dependencies.py
api/main.py
api/models.py
sdk/__init__.py
services/__init__.py
services/bounding_boxes.py
services/file_storage.py
services/gemini_service.py
vlms/__init__.py
vla_sdk-0.0.0.dist-info/METADATA
vla_sdk-0.0.0.dist-info/WHEEL
vla_sdk-0.0.0.dist-info/top_level.txt
vla_sdk-0.0.0.dist-info/RECORD
